pytorch_nd_semiconv/__init__.py
pytorch_nd_semiconv/_compiled_conv.py
pytorch_nd_semiconv/_conv_modules.py
pytorch_nd_semiconv/_learned_pos_def.py
pytorch_nd_semiconv/_quadratic.py
pytorch_nd_semiconv/_sf_broadcast.py
pytorch_nd_semiconv/_sf_select.py
pytorch_nd_semiconv/_sf_select_codegen.py
pytorch_nd_semiconv/_sf_subtract.py
pytorch_nd_semiconv/_sf_subtract_codegen.py
pytorch_nd_semiconv/_unfold_view.py
pytorch_nd_semiconv/_utils.py
pytorch_nd_semiconv/py.typed
pytorch_nd_semiconv-0.1.2.dist-info/METADATA
pytorch_nd_semiconv-0.1.2.dist-info/WHEEL
pytorch_nd_semiconv-0.1.2.dist-info/licenses/LICENSE
pytorch_nd_semiconv-0.1.2.dist-info/RECORD
