Metadata-Version: 2.4
Name: pytorch-nd-semiconv
Version: 0.1.2
Summary: N-dimensional convolutional operators for various semifields
Author-email: Peter Adema <p.j.adema@uva.nl>
License-Expression: MIT
License-File: LICENSE
Requires-Python: >=3.10
Requires-Dist: numba-cuda>=0.9.0
Requires-Dist: pytorch-numba-extension-jit>=0.1.6
Requires-Dist: torch>=2.6.0
Requires-Dist: uuid>=1.30
